poetry_plugin_taskipy/__init__.py
poetry_plugin_taskipy/commands.py
poetry_plugin_taskipy/plugin.py
poetry_plugin_taskipy-1.0.0.dist-info/LICENSE
poetry_plugin_taskipy-1.0.0.dist-info/METADATA
poetry_plugin_taskipy-1.0.0.dist-info/WHEEL
poetry_plugin_taskipy-1.0.0.dist-info/entry_points.txt
poetry_plugin_taskipy-1.0.0.dist-info/RECORD
