Metadata-Version: 2.1
Name: poetry-plugin-taskipy
Version: 1.0.0
Summary: Poetry plugin for taskipy
Home-page: https://github.com/taskipy/poetry-plugin-taskipy
License: MIT
Keywords: tasks,task runner,development,poetry,plugin
Author: Taskipy Team
Requires-Python: >=3.7,<4.0
Classifier: Intended Audience :: Developers
Classifier: License :: OSI Approved :: MIT License
Classifier: Programming Language :: Python :: 3
Classifier: Programming Language :: Python :: 3.7
Classifier: Programming Language :: Python :: 3.8
Classifier: Programming Language :: Python :: 3.9
Classifier: Programming Language :: Python :: 3.10
Classifier: Programming Language :: Python :: 3.11
Classifier: Topic :: Software Development :: Build Tools
Requires-Dist: poetry (>=1.4.2,<2.0.0)
Requires-Dist: taskipy (>=1.11.0,<2.0.0)
Project-URL: Repository, https://github.com/taskipy/poetry-plugin-taskipy
